riot_transmute/__init__.py
riot_transmute/common/__init__.py
riot_transmute/common/constants.py
riot_transmute/common/get_player.py
riot_transmute/common/iso_date_from_ms.py
riot_transmute/logger.py
riot_transmute/match_timeline_to_game.py
riot_transmute/match_to_game.py
riot_transmute/merge_match_and_timeline.py
riot_transmute/v4/__init__.py
riot_transmute/v4/match_timeline_to_game.py
riot_transmute/v4/match_to_game.py
riot_transmute/v5/__init__.py
riot_transmute/v5/match_timeline_to_game.py
riot_transmute/v5/match_to_game.py
riot_transmute-2.1.2.dist-info/LICENSE
riot_transmute-2.1.2.dist-info/WHEEL
riot_transmute-2.1.2.dist-info/METADATA
riot_transmute-2.1.2.dist-info/RECORD
